{
    "money": 15749,
    "listLevelsDataSave": [
        {
            "level": 1,
            "rating": 15,
            "pricePerVisit": 20,
            "listObjectsDataSave": [
                {
                    "position": {
                        "x": -26.053691864013673,
                        "y": 0.000011444091796875,
                        "z": 29.955114364624025
                    },
                    "rotation": {
                        "x": 0.0,
                        "y": 0.0,
                        "z": 0.0,
                        "w": 1.0
                    },
                    "indexInBuildingManagerList": 0
                },
                {
                    "position": {
                        "x": -37.65563201904297,
                        "y": 0.000011444091796875,
                        "z": 38.948402404785159
                    },
                    "rotation": {
                        "x": 4.470348002882929e-8,
                        "y": -0.7071067690849304,
                        "z": 0.0,
                        "w": 0.7071068286895752
                    },
                    "indexInBuildingManagerList": 2
                },
                {
                    "position": {
                        "x": -36.488582611083987,
                        "y": 0.00005340576171875,
                        "z": 44.50914764404297
                    },
                    "rotation": {
                        "x": 2.9802322387695315e-8,
                        "y": -0.7071067690849304,
                        "z": 1.4901161193847657e-8,
                        "w": 0.7071068286895752
                    },
                    "indexInBuildingManagerList": 3
                },
                {
                    "position": {
                        "x": -36.64103317260742,
                        "y": 0.000080108642578125,
                        "z": 41.87430191040039
                    },
                    "rotation": {
                        "x": 4.470348002882929e-8,
                        "y": -0.7071067690849304,
                        "z": 0.0,
                        "w": 0.7071068286895752
                    },
                    "indexInBuildingManagerList": 4
                },
                {
                    "position": {
                        "x": -37.14678955078125,
                        "y": 0.0000095367431640625,
                        "z": 48.06029510498047
                    },
                    "rotation": {
                        "x": 0.0,
                        "y": 0.7071068286895752,
                        "z": 5.960463766996327e-8,
                        "w": 0.7071067690849304
                    },
                    "indexInBuildingManagerList": 5
                },
                {
                    "position": {
                        "x": -38.02217483520508,
                        "y": 0.0000057220458984375,
                        "z": 52.20375061035156
                    },
                    "rotation": {
                        "x": 0.0,
                        "y": 0.7071068286895752,
                        "z": 5.960463766996327e-8,
                        "w": 0.7071067690849304
                    },
                    "indexInBuildingManagerList": 6
                },
                {
                    "position": {
                        "x": -37.76921844482422,
                        "y": 0.0000057220458984375,
                        "z": 56.07481384277344
                    },
                    "rotation": {
                        "x": 0.0,
                        "y": 0.7071068286895752,
                        "z": 5.960463766996327e-8,
                        "w": 0.7071067690849304
                    },
                    "indexInBuildingManagerList": 7
                },
                {
                    "position": {
                        "x": -28.782032012939454,
                        "y": 0.000003814697265625,
                        "z": 41.407440185546878
                    },
                    "rotation": {
                        "x": 0.0,
                        "y": 0.7071068286895752,
                        "z": 5.960463766996327e-8,
                        "w": 0.7071067690849304
                    },
                    "indexInBuildingManagerList": 8
                },
                {
                    "position": {
                        "x": -29.482295989990236,
                        "y": 0.000003814697265625,
                        "z": 44.28642654418945
                    },
                    "rotation": {
                        "x": 0.0,
                        "y": 0.7071068286895752,
                        "z": 5.960463766996327e-8,
                        "w": 0.7071067690849304
                    },
                    "indexInBuildingManagerList": 9
                },
                {
                    "position": {
                        "x": -31.096935272216798,
                        "y": 0.2700061798095703,
                        "z": 47.92414093017578
                    },
                    "rotation": {
                        "x": 0.0,
                        "y": 0.7071068286895752,
                        "z": 5.960463766996327e-8,
                        "w": 0.7071067690849304
                    },
                    "indexInBuildingManagerList": 10
                },
                {
                    "position": {
                        "x": -31.330341339111329,
                        "y": 0.00000762939453125,
                        "z": 51.26997375488281
                    },
                    "rotation": {
                        "x": 0.0,
                        "y": 0.7071068286895752,
                        "z": 5.960463766996327e-8,
                        "w": 0.7071067690849304
                    },
                    "indexInBuildingManagerList": 11
                },
                {
                    "position": {
                        "x": -32.10847091674805,
                        "y": 0.00000762939453125,
                        "z": 53.75995635986328
                    },
                    "rotation": {
                        "x": 0.0,
                        "y": 0.7071068286895752,
                        "z": 5.960463766996327e-8,
                        "w": 0.7071067690849304
                    },
                    "indexInBuildingManagerList": 12
                },
                {
                    "position": {
                        "x": -38.58613967895508,
                        "y": 0.00002288818359375,
                        "z": 44.44190979003906
                    },
                    "rotation": {
                        "x": 4.470348002882929e-8,
                        "y": -0.7071067690849304,
                        "z": 0.0,
                        "w": 0.7071068286895752
                    },
                    "indexInBuildingManagerList": 3
                },
                {
                    "position": {
                        "x": -36.40742874145508,
                        "y": 0.000091552734375,
                        "z": 40.24011993408203
                    },
                    "rotation": {
                        "x": 4.470348002882929e-8,
                        "y": -0.7071067690849304,
                        "z": 0.0,
                        "w": 0.7071068286895752
                    },
                    "indexInBuildingManagerList": 4
                },
                {
                    "position": {
                        "x": -37.73014450073242,
                        "y": 0.000064849853515625,
                        "z": 59.381492614746097
                    },
                    "rotation": {
                        "x": 0.0,
                        "y": 0.7071068286895752,
                        "z": 5.960463766996327e-8,
                        "w": 0.7071067690849304
                    },
                    "indexInBuildingManagerList": 7
                },
                {
                    "position": {
                        "x": -33.95635223388672,
                        "y": 0.000003814697265625,
                        "z": 60.27647399902344
                    },
                    "rotation": {
                        "x": -5.960463766996327e-8,
                        "y": 1.0,
                        "z": 4.470348002882929e-8,
                        "w": -8.940696005765858e-8
                    },
                    "indexInBuildingManagerList": 6
                },
                {
                    "position": {
                        "x": -25.085956573486329,
                        "y": 0.000011444091796875,
                        "z": 46.89295959472656
                    },
                    "rotation": {
                        "x": 0.0,
                        "y": 0.7071068286895752,
                        "z": 5.960463766996327e-8,
                        "w": 0.7071067690849304
                    },
                    "indexInBuildingManagerList": 8
                },
                {
                    "position": {
                        "x": -25.63055419921875,
                        "y": 0.0000019073486328125,
                        "z": 49.77196502685547
                    },
                    "rotation": {
                        "x": 0.0,
                        "y": 0.7071068286895752,
                        "z": 5.960463766996327e-8,
                        "w": 0.7071067690849304
                    },
                    "indexInBuildingManagerList": 9
                },
                {
                    "position": {
                        "x": -37.67787551879883,
                        "y": 0.0000209808349609375,
                        "z": 37.49183654785156
                    },
                    "rotation": {
                        "x": 4.470348002882929e-8,
                        "y": -0.7071067690849304,
                        "z": 0.0,
                        "w": 0.7071068286895752
                    },
                    "indexInBuildingManagerList": 2
                },
                {
                    "position": {
                        "x": -25.111454010009767,
                        "y": 0.00078582763671875,
                        "z": 43.20687484741211
                    },
                    "rotation": {
                        "x": 1.4901161193847657e-8,
                        "y": -0.7071070671081543,
                        "z": -4.470348358154297e-8,
                        "w": -0.7071065902709961
                    },
                    "indexInBuildingManagerList": 5
                },
                {
                    "position": {
                        "x": -37.8958854675293,
                        "y": 0.000003814697265625,
                        "z": 25.73297882080078
                    },
                    "rotation": {
                        "x": 0.0,
                        "y": -1.7881392011531717e-7,
                        "z": -1.4901159417490817e-8,
                        "w": -1.0
                    },
                    "indexInBuildingManagerList": 1
                },
                {
                    "position": {
                        "x": -12.374591827392579,
                        "y": 0.0000400543212890625,
                        "z": 31.94593048095703
                    },
                    "rotation": {
                        "x": 0.0,
                        "y": 1.0,
                        "z": 0.0,
                        "w": 0.0
                    },
                    "indexInBuildingManagerList": 1
                },
                {
                    "position": {
                        "x": -17.947006225585939,
                        "y": 0.0000667572021484375,
                        "z": 31.66171646118164
                    },
                    "rotation": {
                        "x": 0.0,
                        "y": 1.0,
                        "z": 0.0,
                        "w": 0.0
                    },
                    "indexInBuildingManagerList": 1
                },
                {
                    "position": {
                        "x": -38.158355712890628,
                        "y": 0.0000057220458984375,
                        "z": 32.10920715332031
                    },
                    "rotation": {
                        "x": 0.0,
                        "y": 1.0,
                        "z": 0.0,
                        "w": 0.0
                    },
                    "indexInBuildingManagerList": 1
                },
                {
                    "position": {
                        "x": -12.38351058959961,
                        "y": 0.0000095367431640625,
                        "z": 23.686046600341798
                    },
                    "rotation": {
                        "x": 0.0,
                        "y": -1.4901159772762186e-7,
                        "z": -7.4505797087454088e-9,
                        "w": -1.0
                    },
                    "indexInBuildingManagerList": 1
                }
            ]
        }
    ]
}